topsis_python/topsis.py
TOPSIS_SANYAM_GOYAL_102297005-0.0.1.dist-info/LICENSE.txt
TOPSIS_SANYAM_GOYAL_102297005-0.0.1.dist-info/METADATA
TOPSIS_SANYAM_GOYAL_102297005-0.0.1.dist-info/WHEEL
TOPSIS_SANYAM_GOYAL_102297005-0.0.1.dist-info/entry_points.txt
TOPSIS_SANYAM_GOYAL_102297005-0.0.1.dist-info/top_level.txt
TOPSIS_SANYAM_GOYAL_102297005-0.0.1.dist-info/RECORD
