Metadata-Version: 2.1
Name: TOPSIS-SANYAM-GOYAL-102297005
Version: 0.0.1
Summary: A Python package to find TOPSIS for multi-criteria decision analysis method
Home-page: https://www.github.com/sanyamgoyal401
Author: Sanyam Goyal
Author-email: sanyamgoyal2859@gmail.com
License: MIT
Keywords: topsis,UCS654,TIET,data,science,Prashant Singh Rana
Classifier: Development Status :: 3 - Alpha
Classifier: Intended Audience :: Developers
Classifier: Operating System :: Microsoft :: Windows :: Windows 10
Classifier: Operating System :: POSIX :: Linux
Classifier: License :: OSI Approved :: MIT License
Classifier: Programming Language :: Python :: 3
License-File: LICENSE.txt
Requires-Dist: pandas
Requires-Dist: tabulate
